{
  "selected_threshold": {
    "threshold": 0.1,
    "selection_metric": "detector_f1_then_low_false_positive_rate",
    "selected_row": {
      "threshold": 0.1,
      "route_to_char_rate": 0.273531,
      "accuracy": 0.986012,
      "precision": 0.996701,
      "recall": 0.954201,
      "f1": 0.974988,
      "true_positive": 3021.0,
      "false_positive": 10.0,
      "true_negative": 7905.0,
      "false_negative": 145.0,
      "false_positive_rate": 0.001263,
      "false_negative_rate": 0.045799
    },
    "min_alpha_chars": 12,
    "min_words": 3,
    "no_accent_variants": [
      "no_accent",
      "mixed_no_accent"
    ]
  },
  "detector_overall": [
    {
      "scope": "overall",
      "accuracy": 0.984839,
      "precision": 0.993904,
      "recall": 0.95278,
      "f1": 0.972908,
      "true_positive": 6033,
      "false_positive": 37,
      "true_negative": 15793,
      "false_negative": 299,
      "false_positive_rate": 0.002337,
      "false_negative_rate": 0.04722
    }
  ],
  "detector_by_variant": [
    {
      "scope": "variant",
      "variant": "clean",
      "total": 3166,
      "route_to_char_svm": 7,
      "route_to_phobert": 3159,
      "route_to_char_rate": 0.002211,
      "true_no_accent_variant": false,
      "mean_accented_ratio": 0.275389,
      "median_accented_ratio": 0.272727
    },
    {
      "scope": "variant",
      "variant": "mixed_light",
      "total": 3166,
      "route_to_char_svm": 9,
      "route_to_phobert": 3157,
      "route_to_char_rate": 0.002843,
      "true_no_accent_variant": false,
      "mean_accented_ratio": 0.271621,
      "median_accented_ratio": 0.27027
    },
    {
      "scope": "variant",
      "variant": "mixed_no_accent",
      "total": 3166,
      "route_to_char_svm": 3013,
      "route_to_phobert": 153,
      "route_to_char_rate": 0.951674,
      "true_no_accent_variant": true,
      "mean_accented_ratio": 0.0,
      "median_accented_ratio": 0.0
    },
    {
      "scope": "variant",
      "variant": "no_accent",
      "total": 3166,
      "route_to_char_svm": 3020,
      "route_to_phobert": 146,
      "route_to_char_rate": 0.953885,
      "true_no_accent_variant": true,
      "mean_accented_ratio": 0.0,
      "median_accented_ratio": 0.0
    },
    {
      "scope": "variant",
      "variant": "teencode_light",
      "total": 3166,
      "route_to_char_svm": 7,
      "route_to_phobert": 3159,
      "route_to_char_rate": 0.002211,
      "true_no_accent_variant": false,
      "mean_accented_ratio": 0.272048,
      "median_accented_ratio": 0.27027
    },
    {
      "scope": "variant",
      "variant": "typo_light",
      "total": 3166,
      "route_to_char_svm": 7,
      "route_to_phobert": 3159,
      "route_to_char_rate": 0.002211,
      "true_no_accent_variant": false,
      "mean_accented_ratio": 0.275022,
      "median_accented_ratio": 0.272727
    },
    {
      "scope": "variant",
      "variant": "typo_medium",
      "total": 3166,
      "route_to_char_svm": 7,
      "route_to_phobert": 3159,
      "route_to_char_rate": 0.002211,
      "true_no_accent_variant": false,
      "mean_accented_ratio": 0.274831,
      "median_accented_ratio": 0.272727
    }
  ],
  "comparison": [
    {
      "task": "sentiment",
      "system": "oracle_router",
      "variant": "clean",
      "noise_type": "clean",
      "noise_level": "none",
      "num_samples": 3166,
      "accuracy": 0.931459,
      "macro_precision": 0.838886,
      "macro_recall": 0.809982,
      "macro_f1": 0.822815,
      "weighted_precision": 0.928643,
      "weighted_recall": 0.931459,
      "weighted_f1": 0.929772,
      "variant_order": 0,
      "clean_macro_f1": 0.822815,
      "variant_macro_f1": 0.822815,
      "macro_f1_drop": 0.0,
      "macro_f1_relative_drop_percent": 0.0,
      "rank_macro_f1_within_variant": 1,
      "phobert_only_macro_f1": 0.822815,
      "phobert_only_accuracy": 0.931459,
      "oracle_router_macro_f1": 0.822815,
      "oracle_router_accuracy": 0.931459,
      "macro_f1_gain_vs_phobert": 0.0,
      "accuracy_gain_vs_phobert": 0.0,
      "macro_f1_gap_to_oracle": 0.0
    },
    {
      "task": "sentiment",
      "system": "phobert_only",
      "variant": "clean",
      "noise_type": "clean",
      "noise_level": "none",
      "num_samples": 3166,
      "accuracy": 0.931459,
      "macro_precision": 0.838886,
      "macro_recall": 0.809982,
      "macro_f1": 0.822815,
      "weighted_precision": 0.928643,
      "weighted_recall": 0.931459,
      "weighted_f1": 0.929772,
      "variant_order": 0,
      "clean_macro_f1": 0.822815,
      "variant_macro_f1": 0.822815,
      "macro_f1_drop": 0.0,
      "macro_f1_relative_drop_percent": 0.0,
      "rank_macro_f1_within_variant": 1,
      "phobert_only_macro_f1": 0.822815,
      "phobert_only_accuracy": 0.931459,
      "oracle_router_macro_f1": 0.822815,
      "oracle_router_accuracy": 0.931459,
      "macro_f1_gain_vs_phobert": 0.0,
      "accuracy_gain_vs_phobert": 0.0,
      "macro_f1_gap_to_oracle": 0.0
    },
    {
      "task": "sentiment",
      "system": "robust_router",
      "variant": "clean",
      "noise_type": "clean",
      "noise_level": "none",
      "num_samples": 3166,
      "accuracy": 0.931459,
      "macro_precision": 0.838864,
      "macro_recall": 0.809982,
      "macro_f1": 0.822803,
      "weighted_precision": 0.928647,
      "weighted_recall": 0.931459,
      "weighted_f1": 0.929773,
      "variant_order": 0,
      "clean_macro_f1": 0.822803,
      "variant_macro_f1": 0.822803,
      "macro_f1_drop": 0.0,
      "macro_f1_relative_drop_percent": 0.0,
      "rank_macro_f1_within_variant": 2,
      "phobert_only_macro_f1": 0.822815,
      "phobert_only_accuracy": 0.931459,
      "oracle_router_macro_f1": 0.822815,
      "oracle_router_accuracy": 0.931459,
      "macro_f1_gain_vs_phobert": -1.2e-05,
      "accuracy_gain_vs_phobert": 0.0,
      "macro_f1_gap_to_oracle": 1.2e-05
    },
    {
      "task": "sentiment",
      "system": "tfidf_char_svm_only",
      "variant": "clean",
      "noise_type": "clean",
      "noise_level": "none",
      "num_samples": 3166,
      "accuracy": 0.875237,
      "macro_precision": 0.73445,
      "macro_recall": 0.743985,
      "macro_f1": 0.738784,
      "weighted_precision": 0.878414,
      "weighted_recall": 0.875237,
      "weighted_f1": 0.876528,
      "variant_order": 0,
      "clean_macro_f1": 0.738784,
      "variant_macro_f1": 0.738784,
      "macro_f1_drop": 0.0,
      "macro_f1_relative_drop_percent": 0.0,
      "rank_macro_f1_within_variant": 3,
      "phobert_only_macro_f1": 0.822815,
      "phobert_only_accuracy": 0.931459,
      "oracle_router_macro_f1": 0.822815,
      "oracle_router_accuracy": 0.931459,
      "macro_f1_gain_vs_phobert": -0.084031,
      "accuracy_gain_vs_phobert": -0.056222,
      "macro_f1_gap_to_oracle": 0.084031
    },
    {
      "task": "sentiment",
      "system": "oracle_router",
      "variant": "typo_light",
      "noise_type": "typo",
      "noise_level": "light",
      "num_samples": 3166,
      "accuracy": 0.929248,
      "macro_precision": 0.837781,
      "macro_recall": 0.806675,
      "macro_f1": 0.820352,
      "weighted_precision": 0.926269,
      "weighted_recall": 0.929248,
      "weighted_f1": 0.927437,
      "variant_order": 1,
      "clean_macro_f1": 0.822815,
      "variant_macro_f1": 0.820352,
      "macro_f1_drop": 0.002463,
      "macro_f1_relative_drop_percent": 0.2993,
      "rank_macro_f1_within_variant": 1,
      "phobert_only_macro_f1": 0.820352,
      "phobert_only_accuracy": 0.929248,
      "oracle_router_macro_f1": 0.820352,
      "oracle_router_accuracy": 0.929248,
      "macro_f1_gain_vs_phobert": 0.0,
      "accuracy_gain_vs_phobert": 0.0,
      "macro_f1_gap_to_oracle": 0.0
    },
    {
      "task": "sentiment",
      "system": "phobert_only",
      "variant": "typo_light",
      "noise_type": "typo",
      "noise_level": "light",
      "num_samples": 3166,
      "accuracy": 0.929248,
      "macro_precision": 0.837781,
      "macro_recall": 0.806675,
      "macro_f1": 0.820352,
      "weighted_precision": 0.926269,
      "weighted_recall": 0.929248,
      "weighted_f1": 0.927437,
      "variant_order": 1,
      "clean_macro_f1": 0.822815,
      "variant_macro_f1": 0.820352,
      "macro_f1_drop": 0.002463,
      "macro_f1_relative_drop_percent": 0.2993,
      "rank_macro_f1_within_variant": 1,
      "phobert_only_macro_f1": 0.820352,
      "phobert_only_accuracy": 0.929248,
      "oracle_router_macro_f1": 0.820352,
      "oracle_router_accuracy": 0.929248,
      "macro_f1_gain_vs_phobert": 0.0,
      "accuracy_gain_vs_phobert": 0.0,
      "macro_f1_gap_to_oracle": 0.0
    },
    {
      "task": "sentiment",
      "system": "robust_router",
      "variant": "typo_light",
      "noise_type": "typo",
      "noise_level": "light",
      "num_samples": 3166,
      "accuracy": 0.929248,
      "macro_precision": 0.837759,
      "macro_recall": 0.806675,
      "macro_f1": 0.82034,
      "weighted_precision": 0.926274,
      "weighted_recall": 0.929248,
      "weighted_f1": 0.927438,
      "variant_order": 1,
      "clean_macro_f1": 0.822803,
      "variant_macro_f1": 0.82034,
      "macro_f1_drop": 0.002463,
      "macro_f1_relative_drop_percent": 0.2993,
      "rank_macro_f1_within_variant": 2,
      "phobert_only_macro_f1": 0.820352,
      "phobert_only_accuracy": 0.929248,
      "oracle_router_macro_f1": 0.820352,
      "oracle_router_accuracy": 0.929248,
      "macro_f1_gain_vs_phobert": -1.2e-05,
      "accuracy_gain_vs_phobert": 0.0,
      "macro_f1_gap_to_oracle": 1.2e-05
    },
    {
      "task": "sentiment",
      "system": "tfidf_char_svm_only",
      "variant": "typo_light",
      "noise_type": "typo",
      "noise_level": "light",
      "num_samples": 3166,
      "accuracy": 0.873342,
      "macro_precision": 0.726814,
      "macro_recall": 0.73726,
      "macro_f1": 0.731545,
      "weighted_precision": 0.87703,
      "weighted_recall": 0.873342,
      "weighted_f1": 0.874915,
      "variant_order": 1,
      "clean_macro_f1": 0.738784,
      "variant_macro_f1": 0.731545,
      "macro_f1_drop": 0.007239,
      "macro_f1_relative_drop_percent": 0.9799,
      "rank_macro_f1_within_variant": 3,
      "phobert_only_macro_f1": 0.820352,
      "phobert_only_accuracy": 0.929248,
      "oracle_router_macro_f1": 0.820352,
      "oracle_router_accuracy": 0.929248,
      "macro_f1_gain_vs_phobert": -0.088807,
      "accuracy_gain_vs_phobert": -0.055906,
      "macro_f1_gap_to_oracle": 0.088807
    },
    {
      "task": "sentiment",
      "system": "robust_router",
      "variant": "typo_medium",
      "noise_type": "typo",
      "noise_level": "medium",
      "num_samples": 3166,
      "accuracy": 0.927669,
      "macro_precision": 0.833327,
      "macro_recall": 0.809038,
      "macro_f1": 0.820027,
      "weighted_precision": 0.925201,
      "weighted_recall": 0.927669,
      "weighted_f1": 0.926236,
      "variant_order": 2,
      "clean_macro_f1": 0.822803,
      "variant_macro_f1": 0.820027,
      "macro_f1_drop": 0.002776,
      "macro_f1_relative_drop_percent": 0.3374,
      "rank_macro_f1_within_variant": 1,
      "phobert_only_macro_f1": 0.818815,
      "phobert_only_accuracy": 0.927353,
      "oracle_router_macro_f1": 0.818815,
      "oracle_router_accuracy": 0.927353,
      "macro_f1_gain_vs_phobert": 0.001212,
      "accuracy_gain_vs_phobert": 0.000316,
      "macro_f1_gap_to_oracle": -0.001212
    },
    {
      "task": "sentiment",
      "system": "oracle_router",
      "variant": "typo_medium",
      "noise_type": "typo",
      "noise_level": "medium",
      "num_samples": 3166,
      "accuracy": 0.927353,
      "macro_precision": 0.830706,
      "macro_recall": 0.808828,
      "macro_f1": 0.818815,
      "weighted_precision": 0.925029,
      "weighted_recall": 0.927353,
      "weighted_f1": 0.926026,
      "variant_order": 2,
      "clean_macro_f1": 0.822815,
      "variant_macro_f1": 0.818815,
      "macro_f1_drop": 0.004,
      "macro_f1_relative_drop_percent": 0.4861,
      "rank_macro_f1_within_variant": 2,
      "phobert_only_macro_f1": 0.818815,
      "phobert_only_accuracy": 0.927353,
      "oracle_router_macro_f1": 0.818815,
      "oracle_router_accuracy": 0.927353,
      "macro_f1_gain_vs_phobert": 0.0,
      "accuracy_gain_vs_phobert": 0.0,
      "macro_f1_gap_to_oracle": 0.0
    },
    {
      "task": "sentiment",
      "system": "phobert_only",
      "variant": "typo_medium",
      "noise_type": "typo",
      "noise_level": "medium",
      "num_samples": 3166,
      "accuracy": 0.927353,
      "macro_precision": 0.830706,
      "macro_recall": 0.808828,
      "macro_f1": 0.818815,
      "weighted_precision": 0.925029,
      "weighted_recall": 0.927353,
      "weighted_f1": 0.926026,
      "variant_order": 2,
      "clean_macro_f1": 0.822815,
      "variant_macro_f1": 0.818815,
      "macro_f1_drop": 0.004,
      "macro_f1_relative_drop_percent": 0.4861,
      "rank_macro_f1_within_variant": 2,
      "phobert_only_macro_f1": 0.818815,
      "phobert_only_accuracy": 0.927353,
      "oracle_router_macro_f1": 0.818815,
      "oracle_router_accuracy": 0.927353,
      "macro_f1_gain_vs_phobert": 0.0,
      "accuracy_gain_vs_phobert": 0.0,
      "macro_f1_gap_to_oracle": 0.0
    },
    {
      "task": "sentiment",
      "system": "tfidf_char_svm_only",
      "variant": "typo_medium",
      "noise_type": "typo",
      "noise_level": "medium",
      "num_samples": 3166,
      "accuracy": 0.870499,
      "macro_precision": 0.725164,
      "macro_recall": 0.738839,
      "macro_f1": 0.731212,
      "weighted_precision": 0.875366,
      "weighted_recall": 0.870499,
      "weighted_f1": 0.872558,
      "variant_order": 2,
      "clean_macro_f1": 0.738784,
      "variant_macro_f1": 0.731212,
      "macro_f1_drop": 0.007572,
      "macro_f1_relative_drop_percent": 1.0249,
      "rank_macro_f1_within_variant": 3,
      "phobert_only_macro_f1": 0.818815,
      "phobert_only_accuracy": 0.927353,
      "oracle_router_macro_f1": 0.818815,
      "oracle_router_accuracy": 0.927353,
      "macro_f1_gain_vs_phobert": -0.087603,
      "accuracy_gain_vs_phobert": -0.056854,
      "macro_f1_gap_to_oracle": 0.087603
    },
    {
      "task": "sentiment",
      "system": "oracle_router",
      "variant": "teencode_light",
      "noise_type": "teencode",
      "noise_level": "light",
      "num_samples": 3166,
      "accuracy": 0.924826,
      "macro_precision": 0.824704,
      "macro_recall": 0.805122,
      "macro_f1": 0.814152,
      "weighted_precision": 0.922626,
      "weighted_recall": 0.924826,
      "weighted_f1": 0.923594,
      "variant_order": 3,
      "clean_macro_f1": 0.822815,
      "variant_macro_f1": 0.814152,
      "macro_f1_drop": 0.008663,
      "macro_f1_relative_drop_percent": 1.0528,
      "rank_macro_f1_within_variant": 1,
      "phobert_only_macro_f1": 0.814152,
      "phobert_only_accuracy": 0.924826,
      "oracle_router_macro_f1": 0.814152,
      "oracle_router_accuracy": 0.924826,
      "macro_f1_gain_vs_phobert": 0.0,
      "accuracy_gain_vs_phobert": 0.0,
      "macro_f1_gap_to_oracle": 0.0
    },
    {
      "task": "sentiment",
      "system": "phobert_only",
      "variant": "teencode_light",
      "noise_type": "teencode",
      "noise_level": "light",
      "num_samples": 3166,
      "accuracy": 0.924826,
      "macro_precision": 0.824704,
      "macro_recall": 0.805122,
      "macro_f1": 0.814152,
      "weighted_precision": 0.922626,
      "weighted_recall": 0.924826,
      "weighted_f1": 0.923594,
      "variant_order": 3,
      "clean_macro_f1": 0.822815,
      "variant_macro_f1": 0.814152,
      "macro_f1_drop": 0.008663,
      "macro_f1_relative_drop_percent": 1.0528,
      "rank_macro_f1_within_variant": 1,
      "phobert_only_macro_f1": 0.814152,
      "phobert_only_accuracy": 0.924826,
      "oracle_router_macro_f1": 0.814152,
      "oracle_router_accuracy": 0.924826,
      "macro_f1_gain_vs_phobert": 0.0,
      "accuracy_gain_vs_phobert": 0.0,
      "macro_f1_gap_to_oracle": 0.0
    },
    {
      "task": "sentiment",
      "system": "robust_router",
      "variant": "teencode_light",
      "noise_type": "teencode",
      "noise_level": "light",
      "num_samples": 3166,
      "accuracy": 0.924826,
      "macro_precision": 0.824677,
      "macro_recall": 0.805122,
      "macro_f1": 0.814139,
      "weighted_precision": 0.922623,
      "weighted_recall": 0.924826,
      "weighted_f1": 0.923594,
      "variant_order": 3,
      "clean_macro_f1": 0.822803,
      "variant_macro_f1": 0.814139,
      "macro_f1_drop": 0.008664,
      "macro_f1_relative_drop_percent": 1.053,
      "rank_macro_f1_within_variant": 2,
      "phobert_only_macro_f1": 0.814152,
      "phobert_only_accuracy": 0.924826,
      "oracle_router_macro_f1": 0.814152,
      "oracle_router_accuracy": 0.924826,
      "macro_f1_gain_vs_phobert": -1.3e-05,
      "accuracy_gain_vs_phobert": 0.0,
      "macro_f1_gap_to_oracle": 1.3e-05
    },
    {
      "task": "sentiment",
      "system": "tfidf_char_svm_only",
      "variant": "teencode_light",
      "noise_type": "teencode",
      "noise_level": "light",
      "num_samples": 3166,
      "accuracy": 0.869236,
      "macro_precision": 0.725994,
      "macro_recall": 0.742901,
      "macro_f1": 0.733458,
      "weighted_precision": 0.874557,
      "weighted_recall": 0.869236,
      "weighted_f1": 0.871656,
      "variant_order": 3,
      "clean_macro_f1": 0.738784,
      "variant_macro_f1": 0.733458,
      "macro_f1_drop": 0.005326,
      "macro_f1_relative_drop_percent": 0.7209,
      "rank_macro_f1_within_variant": 3,
      "phobert_only_macro_f1": 0.814152,
      "phobert_only_accuracy": 0.924826,
      "oracle_router_macro_f1": 0.814152,
      "oracle_router_accuracy": 0.924826,
      "macro_f1_gain_vs_phobert": -0.080694,
      "accuracy_gain_vs_phobert": -0.05559,
      "macro_f1_gap_to_oracle": 0.080694
    },
    {
      "task": "sentiment",
      "system": "robust_router",
      "variant": "mixed_light",
      "noise_type": "mixed",
      "noise_level": "light",
      "num_samples": 3166,
      "accuracy": 0.921668,
      "macro_precision": 0.825718,
      "macro_recall": 0.804623,
      "macro_f1": 0.814312,
      "weighted_precision": 0.919459,
      "weighted_recall": 0.921668,
      "weighted_f1": 0.920412,
      "variant_order": 4,
      "clean_macro_f1": 0.822803,
      "variant_macro_f1": 0.814312,
      "macro_f1_drop": 0.008491,
      "macro_f1_relative_drop_percent": 1.032,
      "rank_macro_f1_within_variant": 1,
      "phobert_only_macro_f1": 0.813839,
      "phobert_only_accuracy": 0.921668,
      "oracle_router_macro_f1": 0.813839,
      "oracle_router_accuracy": 0.921668,
      "macro_f1_gain_vs_phobert": 0.000473,
      "accuracy_gain_vs_phobert": 0.0,
      "macro_f1_gap_to_oracle": -0.000473
    },
    {
      "task": "sentiment",
      "system": "oracle_router",
      "variant": "mixed_light",
      "noise_type": "mixed",
      "noise_level": "light",
      "num_samples": 3166,
      "accuracy": 0.921668,
      "macro_precision": 0.824602,
      "macro_recall": 0.804623,
      "macro_f1": 0.813839,
      "weighted_precision": 0.919544,
      "weighted_recall": 0.921668,
      "weighted_f1": 0.920467,
      "variant_order": 4,
      "clean_macro_f1": 0.822815,
      "variant_macro_f1": 0.813839,
      "macro_f1_drop": 0.008976,
      "macro_f1_relative_drop_percent": 1.0909,
      "rank_macro_f1_within_variant": 2,
      "phobert_only_macro_f1": 0.813839,
      "phobert_only_accuracy": 0.921668,
      "oracle_router_macro_f1": 0.813839,
      "oracle_router_accuracy": 0.921668,
      "macro_f1_gain_vs_phobert": 0.0,
      "accuracy_gain_vs_phobert": 0.0,
      "macro_f1_gap_to_oracle": 0.0
    },
    {
      "task": "sentiment",
      "system": "phobert_only",
      "variant": "mixed_light",
      "noise_type": "mixed",
      "noise_level": "light",
      "num_samples": 3166,
      "accuracy": 0.921668,
      "macro_precision": 0.824602,
      "macro_recall": 0.804623,
      "macro_f1": 0.813839,
      "weighted_precision": 0.919544,
      "weighted_recall": 0.921668,
      "weighted_f1": 0.920467,
      "variant_order": 4,
      "clean_macro_f1": 0.822815,
      "variant_macro_f1": 0.813839,
      "macro_f1_drop": 0.008976,
      "macro_f1_relative_drop_percent": 1.0909,
      "rank_macro_f1_within_variant": 2,
      "phobert_only_macro_f1": 0.813839,
      "phobert_only_accuracy": 0.921668,
      "oracle_router_macro_f1": 0.813839,
      "oracle_router_accuracy": 0.921668,
      "macro_f1_gain_vs_phobert": 0.0,
      "accuracy_gain_vs_phobert": 0.0,
      "macro_f1_gap_to_oracle": 0.0
    },
    {
      "task": "sentiment",
      "system": "tfidf_char_svm_only",
      "variant": "mixed_light",
      "noise_type": "mixed",
      "noise_level": "light",
      "num_samples": 3166,
      "accuracy": 0.864498,
      "macro_precision": 0.716572,
      "macro_recall": 0.735888,
      "macro_f1": 0.72483,
      "weighted_precision": 0.871245,
      "weighted_recall": 0.864498,
      "weighted_f1": 0.867596,
      "variant_order": 4,
      "clean_macro_f1": 0.738784,
      "variant_macro_f1": 0.72483,
      "macro_f1_drop": 0.013954,
      "macro_f1_relative_drop_percent": 1.8888,
      "rank_macro_f1_within_variant": 3,
      "phobert_only_macro_f1": 0.813839,
      "phobert_only_accuracy": 0.921668,
      "oracle_router_macro_f1": 0.813839,
      "oracle_router_accuracy": 0.921668,
      "macro_f1_gain_vs_phobert": -0.089009,
      "accuracy_gain_vs_phobert": -0.05717,
      "macro_f1_gap_to_oracle": 0.089009
    },
    {
      "task": "sentiment",
      "system": "robust_router",
      "variant": "no_accent",
      "noise_type": "remove_diacritics",
      "noise_level": "medium",
      "num_samples": 3166,
      "accuracy": 0.475679,
      "macro_precision": 0.457774,
      "macro_recall": 0.491209,
      "macro_f1": 0.414838,
      "weighted_precision": 0.61385,
      "weighted_recall": 0.475679,
      "weighted_f1": 0.523529,
      "variant_order": 5,
      "clean_macro_f1": 0.822803,
      "variant_macro_f1": 0.414838,
      "macro_f1_drop": 0.407965,
      "macro_f1_relative_drop_percent": 49.5823,
      "rank_macro_f1_within_variant": 1,
      "phobert_only_macro_f1": 0.339899,
      "phobert_only_accuracy": 0.375237,
      "oracle_router_macro_f1": 0.414024,
      "oracle_router_accuracy": 0.474416,
      "macro_f1_gain_vs_phobert": 0.074939,
      "accuracy_gain_vs_phobert": 0.100442,
      "macro_f1_gap_to_oracle": -0.000814
    },
    {
      "task": "sentiment",
      "system": "oracle_router",
      "variant": "no_accent",
      "noise_type": "remove_diacritics",
      "noise_level": "medium",
      "num_samples": 3166,
      "accuracy": 0.474416,
      "macro_precision": 0.458113,
      "macro_recall": 0.490398,
      "macro_f1": 0.414024,
      "weighted_precision": 0.614779,
      "weighted_recall": 0.474416,
      "weighted_f1": 0.522812,
      "variant_order": 5,
      "clean_macro_f1": 0.822815,
      "variant_macro_f1": 0.414024,
      "macro_f1_drop": 0.408791,
      "macro_f1_relative_drop_percent": 49.682,
      "rank_macro_f1_within_variant": 2,
      "phobert_only_macro_f1": 0.339899,
      "phobert_only_accuracy": 0.375237,
      "oracle_router_macro_f1": 0.414024,
      "oracle_router_accuracy": 0.474416,
      "macro_f1_gain_vs_phobert": 0.074125,
      "accuracy_gain_vs_phobert": 0.099179,
      "macro_f1_gap_to_oracle": 0.0
    },
    {
      "task": "sentiment",
      "system": "tfidf_char_svm_only",
      "variant": "no_accent",
      "noise_type": "remove_diacritics",
      "noise_level": "medium",
      "num_samples": 3166,
      "accuracy": 0.474416,
      "macro_precision": 0.458113,
      "macro_recall": 0.490398,
      "macro_f1": 0.414024,
      "weighted_precision": 0.614779,
      "weighted_recall": 0.474416,
      "weighted_f1": 0.522812,
      "variant_order": 5,
      "clean_macro_f1": 0.738784,
      "variant_macro_f1": 0.414024,
      "macro_f1_drop": 0.32476,
      "macro_f1_relative_drop_percent": 43.9587,
      "rank_macro_f1_within_variant": 2,
      "phobert_only_macro_f1": 0.339899,
      "phobert_only_accuracy": 0.375237,
      "oracle_router_macro_f1": 0.414024,
      "oracle_router_accuracy": 0.474416,
      "macro_f1_gain_vs_phobert": 0.074125,
      "accuracy_gain_vs_phobert": 0.099179,
      "macro_f1_gap_to_oracle": 0.0
    },
    {
      "task": "sentiment",
      "system": "phobert_only",
      "variant": "no_accent",
      "noise_type": "remove_diacritics",
      "noise_level": "medium",
      "num_samples": 3166,
      "accuracy": 0.375237,
      "macro_precision": 0.440888,
      "macro_recall": 0.47334,
      "macro_f1": 0.339899,
      "weighted_precision": 0.596478,
      "weighted_recall": 0.375237,
      "weighted_f1": 0.429524,
      "variant_order": 5,
      "clean_macro_f1": 0.822815,
      "variant_macro_f1": 0.339899,
      "macro_f1_drop": 0.482916,
      "macro_f1_relative_drop_percent": 58.6907,
      "rank_macro_f1_within_variant": 3,
      "phobert_only_macro_f1": 0.339899,
      "phobert_only_accuracy": 0.375237,
      "oracle_router_macro_f1": 0.414024,
      "oracle_router_accuracy": 0.474416,
      "macro_f1_gain_vs_phobert": 0.0,
      "accuracy_gain_vs_phobert": 0.0,
      "macro_f1_gap_to_oracle": 0.074125
    },
    {
      "task": "sentiment",
      "system": "oracle_router",
      "variant": "mixed_no_accent",
      "noise_type": "mixed",
      "noise_level": "medium",
      "num_samples": 3166,
      "accuracy": 0.469678,
      "macro_precision": 0.457614,
      "macro_recall": 0.48842,
      "macro_f1": 0.411,
      "weighted_precision": 0.614751,
      "weighted_recall": 0.469678,
      "weighted_f1": 0.519813,
      "variant_order": 6,
      "clean_macro_f1": 0.822815,
      "variant_macro_f1": 0.411,
      "macro_f1_drop": 0.411815,
      "macro_f1_relative_drop_percent": 50.0495,
      "rank_macro_f1_within_variant": 1,
      "phobert_only_macro_f1": 0.340462,
      "phobert_only_accuracy": 0.371762,
      "oracle_router_macro_f1": 0.411,
      "oracle_router_accuracy": 0.469678,
      "macro_f1_gain_vs_phobert": 0.070538,
      "accuracy_gain_vs_phobert": 0.097916,
      "macro_f1_gap_to_oracle": 0.0
    },
    {
      "task": "sentiment",
      "system": "tfidf_char_svm_only",
      "variant": "mixed_no_accent",
      "noise_type": "mixed",
      "noise_level": "medium",
      "num_samples": 3166,
      "accuracy": 0.469678,
      "macro_precision": 0.457614,
      "macro_recall": 0.48842,
      "macro_f1": 0.411,
      "weighted_precision": 0.614751,
      "weighted_recall": 0.469678,
      "weighted_f1": 0.519813,
      "variant_order": 6,
      "clean_macro_f1": 0.738784,
      "variant_macro_f1": 0.411,
      "macro_f1_drop": 0.327784,
      "macro_f1_relative_drop_percent": 44.368,
      "rank_macro_f1_within_variant": 1,
      "phobert_only_macro_f1": 0.340462,
      "phobert_only_accuracy": 0.371762,
      "oracle_router_macro_f1": 0.411,
      "oracle_router_accuracy": 0.469678,
      "macro_f1_gain_vs_phobert": 0.070538,
      "accuracy_gain_vs_phobert": 0.097916,
      "macro_f1_gap_to_oracle": 0.0
    },
    {
      "task": "sentiment",
      "system": "robust_router",
      "variant": "mixed_no_accent",
      "noise_type": "mixed",
      "noise_level": "medium",
      "num_samples": 3166,
      "accuracy": 0.469994,
      "macro_precision": 0.456365,
      "macro_recall": 0.486816,
      "macro_f1": 0.410707,
      "weighted_precision": 0.612956,
      "weighted_recall": 0.469994,
      "weighted_f1": 0.519681,
      "variant_order": 6,
      "clean_macro_f1": 0.822803,
      "variant_macro_f1": 0.410707,
      "macro_f1_drop": 0.412096,
      "macro_f1_relative_drop_percent": 50.0844,
      "rank_macro_f1_within_variant": 2,
      "phobert_only_macro_f1": 0.340462,
      "phobert_only_accuracy": 0.371762,
      "oracle_router_macro_f1": 0.411,
      "oracle_router_accuracy": 0.469678,
      "macro_f1_gain_vs_phobert": 0.070245,
      "accuracy_gain_vs_phobert": 0.098232,
      "macro_f1_gap_to_oracle": 0.000293
    },
    {
      "task": "sentiment",
      "system": "phobert_only",
      "variant": "mixed_no_accent",
      "noise_type": "mixed",
      "noise_level": "medium",
      "num_samples": 3166,
      "accuracy": 0.371762,
      "macro_precision": 0.445737,
      "macro_recall": 0.471545,
      "macro_f1": 0.340462,
      "weighted_precision": 0.603892,
      "weighted_recall": 0.371762,
      "weighted_f1": 0.430592,
      "variant_order": 6,
      "clean_macro_f1": 0.822815,
      "variant_macro_f1": 0.340462,
      "macro_f1_drop": 0.482353,
      "macro_f1_relative_drop_percent": 58.6223,
      "rank_macro_f1_within_variant": 3,
      "phobert_only_macro_f1": 0.340462,
      "phobert_only_accuracy": 0.371762,
      "oracle_router_macro_f1": 0.411,
      "oracle_router_accuracy": 0.469678,
      "macro_f1_gain_vs_phobert": 0.0,
      "accuracy_gain_vs_phobert": 0.0,
      "macro_f1_gap_to_oracle": 0.070538
    },
    {
      "task": "topic",
      "system": "oracle_router",
      "variant": "clean",
      "noise_type": "clean",
      "noise_level": "none",
      "num_samples": 3166,
      "accuracy": 0.896399,
      "macro_precision": 0.819375,
      "macro_recall": 0.786622,
      "macro_f1": 0.800073,
      "weighted_precision": 0.89333,
      "weighted_recall": 0.896399,
      "weighted_f1": 0.894241,
      "variant_order": 0,
      "clean_macro_f1": 0.800073,
      "variant_macro_f1": 0.800073,
      "macro_f1_drop": 0.0,
      "macro_f1_relative_drop_percent": 0.0,
      "rank_macro_f1_within_variant": 1,
      "phobert_only_macro_f1": 0.800073,
      "phobert_only_accuracy": 0.896399,
      "oracle_router_macro_f1": 0.800073,
      "oracle_router_accuracy": 0.896399,
      "macro_f1_gain_vs_phobert": 0.0,
      "accuracy_gain_vs_phobert": 0.0,
      "macro_f1_gap_to_oracle": 0.0
    },
    {
      "task": "topic",
      "system": "phobert_only",
      "variant": "clean",
      "noise_type": "clean",
      "noise_level": "none",
      "num_samples": 3166,
      "accuracy": 0.896399,
      "macro_precision": 0.819375,
      "macro_recall": 0.786622,
      "macro_f1": 0.800073,
      "weighted_precision": 0.89333,
      "weighted_recall": 0.896399,
      "weighted_f1": 0.894241,
      "variant_order": 0,
      "clean_macro_f1": 0.800073,
      "variant_macro_f1": 0.800073,
      "macro_f1_drop": 0.0,
      "macro_f1_relative_drop_percent": 0.0,
      "rank_macro_f1_within_variant": 1,
      "phobert_only_macro_f1": 0.800073,
      "phobert_only_accuracy": 0.896399,
      "oracle_router_macro_f1": 0.800073,
      "oracle_router_accuracy": 0.896399,
      "macro_f1_gain_vs_phobert": 0.0,
      "accuracy_gain_vs_phobert": 0.0,
      "macro_f1_gap_to_oracle": 0.0
    },
    {
      "task": "topic",
      "system": "robust_router",
      "variant": "clean",
      "noise_type": "clean",
      "noise_level": "none",
      "num_samples": 3166,
      "accuracy": 0.896083,
      "macro_precision": 0.818038,
      "macro_recall": 0.786513,
      "macro_f1": 0.799525,
      "weighted_precision": 0.893043,
      "weighted_recall": 0.896083,
      "weighted_f1": 0.893977,
      "variant_order": 0,
      "clean_macro_f1": 0.799525,
      "variant_macro_f1": 0.799525,
      "macro_f1_drop": 0.0,
      "macro_f1_relative_drop_percent": 0.0,
      "rank_macro_f1_within_variant": 2,
      "phobert_only_macro_f1": 0.800073,
      "phobert_only_accuracy": 0.896399,
      "oracle_router_macro_f1": 0.800073,
      "oracle_router_accuracy": 0.896399,
      "macro_f1_gain_vs_phobert": -0.000548,
      "accuracy_gain_vs_phobert": -0.000316,
      "macro_f1_gap_to_oracle": 0.000548
    },
    {
      "task": "topic",
      "system": "tfidf_char_svm_only",
      "variant": "clean",
      "noise_type": "clean",
      "noise_level": "none",
      "num_samples": 3166,
      "accuracy": 0.833544,
      "macro_precision": 0.707016,
      "macro_recall": 0.765605,
      "macro_f1": 0.732207,
      "weighted_precision": 0.851345,
      "weighted_recall": 0.833544,
      "weighted_f1": 0.840575,
      "variant_order": 0,
      "clean_macro_f1": 0.732207,
      "variant_macro_f1": 0.732207,
      "macro_f1_drop": 0.0,
      "macro_f1_relative_drop_percent": 0.0,
      "rank_macro_f1_within_variant": 3,
      "phobert_only_macro_f1": 0.800073,
      "phobert_only_accuracy": 0.896399,
      "oracle_router_macro_f1": 0.800073,
      "oracle_router_accuracy": 0.896399,
      "macro_f1_gain_vs_phobert": -0.067866,
      "accuracy_gain_vs_phobert": -0.062855,
      "macro_f1_gap_to_oracle": 0.067866
    },
    {
      "task": "topic",
      "system": "oracle_router",
      "variant": "typo_light",
      "noise_type": "typo",
      "noise_level": "light",
      "num_samples": 3166,
      "accuracy": 0.893557,
      "macro_precision": 0.812117,
      "macro_recall": 0.784,
      "macro_f1": 0.795476,
      "weighted_precision": 0.890439,
      "weighted_recall": 0.893557,
      "weighted_f1": 0.891452,
      "variant_order": 1,
      "clean_macro_f1": 0.800073,
      "variant_macro_f1": 0.795476,
      "macro_f1_drop": 0.004597,
      "macro_f1_relative_drop_percent": 0.5746,
      "rank_macro_f1_within_variant": 1,
      "phobert_only_macro_f1": 0.795476,
      "phobert_only_accuracy": 0.893557,
      "oracle_router_macro_f1": 0.795476,
      "oracle_router_accuracy": 0.893557,
      "macro_f1_gain_vs_phobert": 0.0,
      "accuracy_gain_vs_phobert": 0.0,
      "macro_f1_gap_to_oracle": 0.0
    },
    {
      "task": "topic",
      "system": "phobert_only",
      "variant": "typo_light",
      "noise_type": "typo",
      "noise_level": "light",
      "num_samples": 3166,
      "accuracy": 0.893557,
      "macro_precision": 0.812117,
      "macro_recall": 0.784,
      "macro_f1": 0.795476,
      "weighted_precision": 0.890439,
      "weighted_recall": 0.893557,
      "weighted_f1": 0.891452,
      "variant_order": 1,
      "clean_macro_f1": 0.800073,
      "variant_macro_f1": 0.795476,
      "macro_f1_drop": 0.004597,
      "macro_f1_relative_drop_percent": 0.5746,
      "rank_macro_f1_within_variant": 1,
      "phobert_only_macro_f1": 0.795476,
      "phobert_only_accuracy": 0.893557,
      "oracle_router_macro_f1": 0.795476,
      "oracle_router_accuracy": 0.893557,
      "macro_f1_gain_vs_phobert": 0.0,
      "accuracy_gain_vs_phobert": 0.0,
      "macro_f1_gap_to_oracle": 0.0
    },
    {
      "task": "topic",
      "system": "robust_router",
      "variant": "typo_light",
      "noise_type": "typo",
      "noise_level": "light",
      "num_samples": 3166,
      "accuracy": 0.892925,
      "macro_precision": 0.80955,
      "macro_recall": 0.783782,
      "macro_f1": 0.794399,
      "weighted_precision": 0.889887,
      "weighted_recall": 0.892925,
      "weighted_f1": 0.890926,
      "variant_order": 1,
      "clean_macro_f1": 0.799525,
      "variant_macro_f1": 0.794399,
      "macro_f1_drop": 0.005126,
      "macro_f1_relative_drop_percent": 0.6411,
      "rank_macro_f1_within_variant": 2,
      "phobert_only_macro_f1": 0.795476,
      "phobert_only_accuracy": 0.893557,
      "oracle_router_macro_f1": 0.795476,
      "oracle_router_accuracy": 0.893557,
      "macro_f1_gain_vs_phobert": -0.001077,
      "accuracy_gain_vs_phobert": -0.000632,
      "macro_f1_gap_to_oracle": 0.001077
    },
    {
      "task": "topic",
      "system": "tfidf_char_svm_only",
      "variant": "typo_light",
      "noise_type": "typo",
      "noise_level": "light",
      "num_samples": 3166,
      "accuracy": 0.826911,
      "macro_precision": 0.697595,
      "macro_recall": 0.757788,
      "macro_f1": 0.723079,
      "weighted_precision": 0.84677,
      "weighted_recall": 0.826911,
      "weighted_f1": 0.834723,
      "variant_order": 1,
      "clean_macro_f1": 0.732207,
      "variant_macro_f1": 0.723079,
      "macro_f1_drop": 0.009128,
      "macro_f1_relative_drop_percent": 1.2466,
      "rank_macro_f1_within_variant": 3,
      "phobert_only_macro_f1": 0.795476,
      "phobert_only_accuracy": 0.893557,
      "oracle_router_macro_f1": 0.795476,
      "oracle_router_accuracy": 0.893557,
      "macro_f1_gain_vs_phobert": -0.072397,
      "accuracy_gain_vs_phobert": -0.066646,
      "macro_f1_gap_to_oracle": 0.072397
    },
    {
      "task": "topic",
      "system": "robust_router",
      "variant": "typo_medium",
      "noise_type": "typo",
      "noise_level": "medium",
      "num_samples": 3166,
      "accuracy": 0.88566,
      "macro_precision": 0.797177,
      "macro_recall": 0.779024,
      "macro_f1": 0.787098,
      "weighted_precision": 0.884384,
      "weighted_recall": 0.88566,
      "weighted_f1": 0.884775,
      "variant_order": 2,
      "clean_macro_f1": 0.799525,
      "variant_macro_f1": 0.787098,
      "macro_f1_drop": 0.012427,
      "macro_f1_relative_drop_percent": 1.5543,
      "rank_macro_f1_within_variant": 1,
      "phobert_only_macro_f1": 0.78659,
      "phobert_only_accuracy": 0.885344,
      "oracle_router_macro_f1": 0.78659,
      "oracle_router_accuracy": 0.885344,
      "macro_f1_gain_vs_phobert": 0.000508,
      "accuracy_gain_vs_phobert": 0.000316,
      "macro_f1_gap_to_oracle": -0.000508
    },
    {
      "task": "topic",
      "system": "oracle_router",
      "variant": "typo_medium",
      "noise_type": "typo",
      "noise_level": "medium",
      "num_samples": 3166,
      "accuracy": 0.885344,
      "macro_precision": 0.796108,
      "macro_recall": 0.778915,
      "macro_f1": 0.78659,
      "weighted_precision": 0.88415,
      "weighted_recall": 0.885344,
      "weighted_f1": 0.884517,
      "variant_order": 2,
      "clean_macro_f1": 0.800073,
      "variant_macro_f1": 0.78659,
      "macro_f1_drop": 0.013483,
      "macro_f1_relative_drop_percent": 1.6852,
      "rank_macro_f1_within_variant": 2,
      "phobert_only_macro_f1": 0.78659,
      "phobert_only_accuracy": 0.885344,
      "oracle_router_macro_f1": 0.78659,
      "oracle_router_accuracy": 0.885344,
      "macro_f1_gain_vs_phobert": 0.0,
      "accuracy_gain_vs_phobert": 0.0,
      "macro_f1_gap_to_oracle": 0.0
    },
    {
      "task": "topic",
      "system": "phobert_only",
      "variant": "typo_medium",
      "noise_type": "typo",
      "noise_level": "medium",
      "num_samples": 3166,
      "accuracy": 0.885344,
      "macro_precision": 0.796108,
      "macro_recall": 0.778915,
      "macro_f1": 0.78659,
      "weighted_precision": 0.88415,
      "weighted_recall": 0.885344,
      "weighted_f1": 0.884517,
      "variant_order": 2,
      "clean_macro_f1": 0.800073,
      "variant_macro_f1": 0.78659,
      "macro_f1_drop": 0.013483,
      "macro_f1_relative_drop_percent": 1.6852,
      "rank_macro_f1_within_variant": 2,
      "phobert_only_macro_f1": 0.78659,
      "phobert_only_accuracy": 0.885344,
      "oracle_router_macro_f1": 0.78659,
      "oracle_router_accuracy": 0.885344,
      "macro_f1_gain_vs_phobert": 0.0,
      "accuracy_gain_vs_phobert": 0.0,
      "macro_f1_gap_to_oracle": 0.0
    },
    {
      "task": "topic",
      "system": "tfidf_char_svm_only",
      "variant": "typo_medium",
      "noise_type": "typo",
      "noise_level": "medium",
      "num_samples": 3166,
      "accuracy": 0.825963,
      "macro_precision": 0.696582,
      "macro_recall": 0.756501,
      "macro_f1": 0.721417,
      "weighted_precision": 0.847327,
      "weighted_recall": 0.825963,
      "weighted_f1": 0.834351,
      "variant_order": 2,
      "clean_macro_f1": 0.732207,
      "variant_macro_f1": 0.721417,
      "macro_f1_drop": 0.01079,
      "macro_f1_relative_drop_percent": 1.4736,
      "rank_macro_f1_within_variant": 3,
      "phobert_only_macro_f1": 0.78659,
      "phobert_only_accuracy": 0.885344,
      "oracle_router_macro_f1": 0.78659,
      "oracle_router_accuracy": 0.885344,
      "macro_f1_gain_vs_phobert": -0.065173,
      "accuracy_gain_vs_phobert": -0.059381,
      "macro_f1_gap_to_oracle": 0.065173
    },
    {
      "task": "topic",
      "system": "oracle_router",
      "variant": "teencode_light",
      "noise_type": "teencode",
      "noise_level": "light",
      "num_samples": 3166,
      "accuracy": 0.885028,
      "macro_precision": 0.798531,
      "macro_recall": 0.775527,
      "macro_f1": 0.785276,
      "weighted_precision": 0.883074,
      "weighted_recall": 0.885028,
      "weighted_f1": 0.883645,
      "variant_order": 3,
      "clean_macro_f1": 0.800073,
      "variant_macro_f1": 0.785276,
      "macro_f1_drop": 0.014797,
      "macro_f1_relative_drop_percent": 1.8495,
      "rank_macro_f1_within_variant": 1,
      "phobert_only_macro_f1": 0.785276,
      "phobert_only_accuracy": 0.885028,
      "oracle_router_macro_f1": 0.785276,
      "oracle_router_accuracy": 0.885028,
      "macro_f1_gain_vs_phobert": 0.0,
      "accuracy_gain_vs_phobert": 0.0,
      "macro_f1_gap_to_oracle": 0.0
    },
    {
      "task": "topic",
      "system": "phobert_only",
      "variant": "teencode_light",
      "noise_type": "teencode",
      "noise_level": "light",
      "num_samples": 3166,
      "accuracy": 0.885028,
      "macro_precision": 0.798531,
      "macro_recall": 0.775527,
      "macro_f1": 0.785276,
      "weighted_precision": 0.883074,
      "weighted_recall": 0.885028,
      "weighted_f1": 0.883645,
      "variant_order": 3,
      "clean_macro_f1": 0.800073,
      "variant_macro_f1": 0.785276,
      "macro_f1_drop": 0.014797,
      "macro_f1_relative_drop_percent": 1.8495,
      "rank_macro_f1_within_variant": 1,
      "phobert_only_macro_f1": 0.785276,
      "phobert_only_accuracy": 0.885028,
      "oracle_router_macro_f1": 0.785276,
      "oracle_router_accuracy": 0.885028,
      "macro_f1_gain_vs_phobert": 0.0,
      "accuracy_gain_vs_phobert": 0.0,
      "macro_f1_gap_to_oracle": 0.0
    },
    {
      "task": "topic",
      "system": "robust_router",
      "variant": "teencode_light",
      "noise_type": "teencode",
      "noise_level": "light",
      "num_samples": 3166,
      "accuracy": 0.884713,
      "macro_precision": 0.797386,
      "macro_recall": 0.775418,
      "macro_f1": 0.784767,
      "weighted_precision": 0.882825,
      "weighted_recall": 0.884713,
      "weighted_f1": 0.883386,
      "variant_order": 3,
      "clean_macro_f1": 0.799525,
      "variant_macro_f1": 0.784767,
      "macro_f1_drop": 0.014758,
      "macro_f1_relative_drop_percent": 1.8458,
      "rank_macro_f1_within_variant": 2,
      "phobert_only_macro_f1": 0.785276,
      "phobert_only_accuracy": 0.885028,
      "oracle_router_macro_f1": 0.785276,
      "oracle_router_accuracy": 0.885028,
      "macro_f1_gain_vs_phobert": -0.000509,
      "accuracy_gain_vs_phobert": -0.000315,
      "macro_f1_gap_to_oracle": 0.000509
    },
    {
      "task": "topic",
      "system": "tfidf_char_svm_only",
      "variant": "teencode_light",
      "noise_type": "teencode",
      "noise_level": "light",
      "num_samples": 3166,
      "accuracy": 0.822805,
      "macro_precision": 0.694285,
      "macro_recall": 0.756368,
      "macro_f1": 0.719644,
      "weighted_precision": 0.845204,
      "weighted_recall": 0.822805,
      "weighted_f1": 0.83158,
      "variant_order": 3,
      "clean_macro_f1": 0.732207,
      "variant_macro_f1": 0.719644,
      "macro_f1_drop": 0.012563,
      "macro_f1_relative_drop_percent": 1.7158,
      "rank_macro_f1_within_variant": 3,
      "phobert_only_macro_f1": 0.785276,
      "phobert_only_accuracy": 0.885028,
      "oracle_router_macro_f1": 0.785276,
      "oracle_router_accuracy": 0.885028,
      "macro_f1_gain_vs_phobert": -0.065632,
      "accuracy_gain_vs_phobert": -0.062223,
      "macro_f1_gap_to_oracle": 0.065632
    },
    {
      "task": "topic",
      "system": "oracle_router",
      "variant": "mixed_light",
      "noise_type": "mixed",
      "noise_level": "light",
      "num_samples": 3166,
      "accuracy": 0.881238,
      "macro_precision": 0.787292,
      "macro_recall": 0.768844,
      "macro_f1": 0.777107,
      "weighted_precision": 0.878932,
      "weighted_recall": 0.881238,
      "weighted_f1": 0.879876,
      "variant_order": 4,
      "clean_macro_f1": 0.800073,
      "variant_macro_f1": 0.777107,
      "macro_f1_drop": 0.022966,
      "macro_f1_relative_drop_percent": 2.8705,
      "rank_macro_f1_within_variant": 1,
      "phobert_only_macro_f1": 0.777107,
      "phobert_only_accuracy": 0.881238,
      "oracle_router_macro_f1": 0.777107,
      "oracle_router_accuracy": 0.881238,
      "macro_f1_gain_vs_phobert": 0.0,
      "accuracy_gain_vs_phobert": 0.0,
      "macro_f1_gap_to_oracle": 0.0
    },
    {
      "task": "topic",
      "system": "phobert_only",
      "variant": "mixed_light",
      "noise_type": "mixed",
      "noise_level": "light",
      "num_samples": 3166,
      "accuracy": 0.881238,
      "macro_precision": 0.787292,
      "macro_recall": 0.768844,
      "macro_f1": 0.777107,
      "weighted_precision": 0.878932,
      "weighted_recall": 0.881238,
      "weighted_f1": 0.879876,
      "variant_order": 4,
      "clean_macro_f1": 0.800073,
      "variant_macro_f1": 0.777107,
      "macro_f1_drop": 0.022966,
      "macro_f1_relative_drop_percent": 2.8705,
      "rank_macro_f1_within_variant": 1,
      "phobert_only_macro_f1": 0.777107,
      "phobert_only_accuracy": 0.881238,
      "oracle_router_macro_f1": 0.777107,
      "oracle_router_accuracy": 0.881238,
      "macro_f1_gain_vs_phobert": 0.0,
      "accuracy_gain_vs_phobert": 0.0,
      "macro_f1_gap_to_oracle": 0.0
    },
    {
      "task": "topic",
      "system": "robust_router",
      "variant": "mixed_light",
      "noise_type": "mixed",
      "noise_level": "light",
      "num_samples": 3166,
      "accuracy": 0.880922,
      "macro_precision": 0.786147,
      "macro_recall": 0.768407,
      "macro_f1": 0.776402,
      "weighted_precision": 0.878645,
      "weighted_recall": 0.880922,
      "weighted_f1": 0.879594,
      "variant_order": 4,
      "clean_macro_f1": 0.799525,
      "variant_macro_f1": 0.776402,
      "macro_f1_drop": 0.023123,
      "macro_f1_relative_drop_percent": 2.8921,
      "rank_macro_f1_within_variant": 2,
      "phobert_only_macro_f1": 0.777107,
      "phobert_only_accuracy": 0.881238,
      "oracle_router_macro_f1": 0.777107,
      "oracle_router_accuracy": 0.881238,
      "macro_f1_gain_vs_phobert": -0.000705,
      "accuracy_gain_vs_phobert": -0.000316,
      "macro_f1_gap_to_oracle": 0.000705
    },
    {
      "task": "topic",
      "system": "tfidf_char_svm_only",
      "variant": "mixed_light",
      "noise_type": "mixed",
      "noise_level": "light",
      "num_samples": 3166,
      "accuracy": 0.821226,
      "macro_precision": 0.693128,
      "macro_recall": 0.75595,
      "macro_f1": 0.718579,
      "weighted_precision": 0.843638,
      "weighted_recall": 0.821226,
      "weighted_f1": 0.830109,
      "variant_order": 4,
      "clean_macro_f1": 0.732207,
      "variant_macro_f1": 0.718579,
      "macro_f1_drop": 0.013628,
      "macro_f1_relative_drop_percent": 1.8612,
      "rank_macro_f1_within_variant": 3,
      "phobert_only_macro_f1": 0.777107,
      "phobert_only_accuracy": 0.881238,
      "oracle_router_macro_f1": 0.777107,
      "oracle_router_accuracy": 0.881238,
      "macro_f1_gain_vs_phobert": -0.058528,
      "accuracy_gain_vs_phobert": -0.060012,
      "macro_f1_gap_to_oracle": 0.058528
    },
    {
      "task": "topic",
      "system": "robust_router",
      "variant": "no_accent",
      "noise_type": "remove_diacritics",
      "noise_level": "medium",
      "num_samples": 3166,
      "accuracy": 0.442198,
      "macro_precision": 0.349868,
      "macro_recall": 0.36351,
      "macro_f1": 0.300043,
      "weighted_precision": 0.628632,
      "weighted_recall": 0.442198,
      "weighted_f1": 0.50376,
      "variant_order": 5,
      "clean_macro_f1": 0.799525,
      "variant_macro_f1": 0.300043,
      "macro_f1_drop": 0.499482,
      "macro_f1_relative_drop_percent": 62.4723,
      "rank_macro_f1_within_variant": 1,
      "phobert_only_macro_f1": 0.1866,
      "phobert_only_accuracy": 0.252369,
      "oracle_router_macro_f1": 0.295702,
      "oracle_router_accuracy": 0.436197,
      "macro_f1_gain_vs_phobert": 0.113443,
      "accuracy_gain_vs_phobert": 0.189829,
      "macro_f1_gap_to_oracle": -0.004341
    },
    {
      "task": "topic",
      "system": "oracle_router",
      "variant": "no_accent",
      "noise_type": "remove_diacritics",
      "noise_level": "medium",
      "num_samples": 3166,
      "accuracy": 0.436197,
      "macro_precision": 0.348312,
      "macro_recall": 0.350866,
      "macro_f1": 0.295702,
      "weighted_precision": 0.625973,
      "weighted_recall": 0.436197,
      "weighted_f1": 0.499572,
      "variant_order": 5,
      "clean_macro_f1": 0.800073,
      "variant_macro_f1": 0.295702,
      "macro_f1_drop": 0.504371,
      "macro_f1_relative_drop_percent": 63.0406,
      "rank_macro_f1_within_variant": 2,
      "phobert_only_macro_f1": 0.1866,
      "phobert_only_accuracy": 0.252369,
      "oracle_router_macro_f1": 0.295702,
      "oracle_router_accuracy": 0.436197,
      "macro_f1_gain_vs_phobert": 0.109102,
      "accuracy_gain_vs_phobert": 0.183828,
      "macro_f1_gap_to_oracle": 0.0
    },
    {
      "task": "topic",
      "system": "tfidf_char_svm_only",
      "variant": "no_accent",
      "noise_type": "remove_diacritics",
      "noise_level": "medium",
      "num_samples": 3166,
      "accuracy": 0.436197,
      "macro_precision": 0.348312,
      "macro_recall": 0.350866,
      "macro_f1": 0.295702,
      "weighted_precision": 0.625973,
      "weighted_recall": 0.436197,
      "weighted_f1": 0.499572,
      "variant_order": 5,
      "clean_macro_f1": 0.732207,
      "variant_macro_f1": 0.295702,
      "macro_f1_drop": 0.436505,
      "macro_f1_relative_drop_percent": 59.615,
      "rank_macro_f1_within_variant": 2,
      "phobert_only_macro_f1": 0.1866,
      "phobert_only_accuracy": 0.252369,
      "oracle_router_macro_f1": 0.295702,
      "oracle_router_accuracy": 0.436197,
      "macro_f1_gain_vs_phobert": 0.109102,
      "accuracy_gain_vs_phobert": 0.183828,
      "macro_f1_gap_to_oracle": 0.0
    },
    {
      "task": "topic",
      "system": "phobert_only",
      "variant": "no_accent",
      "noise_type": "remove_diacritics",
      "noise_level": "medium",
      "num_samples": 3166,
      "accuracy": 0.252369,
      "macro_precision": 0.320659,
      "macro_recall": 0.312683,
      "macro_f1": 0.1866,
      "weighted_precision": 0.629945,
      "weighted_recall": 0.252369,
      "weighted_f1": 0.320529,
      "variant_order": 5,
      "clean_macro_f1": 0.800073,
      "variant_macro_f1": 0.1866,
      "macro_f1_drop": 0.613473,
      "macro_f1_relative_drop_percent": 76.6771,
      "rank_macro_f1_within_variant": 3,
      "phobert_only_macro_f1": 0.1866,
      "phobert_only_accuracy": 0.252369,
      "oracle_router_macro_f1": 0.295702,
      "oracle_router_accuracy": 0.436197,
      "macro_f1_gain_vs_phobert": 0.0,
      "accuracy_gain_vs_phobert": 0.0,
      "macro_f1_gap_to_oracle": 0.109102
    },
    {
      "task": "topic",
      "system": "robust_router",
      "variant": "mixed_no_accent",
      "noise_type": "mixed",
      "noise_level": "medium",
      "num_samples": 3166,
      "accuracy": 0.437776,
      "macro_precision": 0.355454,
      "macro_recall": 0.370913,
      "macro_f1": 0.304132,
      "weighted_precision": 0.631114,
      "weighted_recall": 0.437776,
      "weighted_f1": 0.500526,
      "variant_order": 6,
      "clean_macro_f1": 0.799525,
      "variant_macro_f1": 0.304132,
      "macro_f1_drop": 0.495393,
      "macro_f1_relative_drop_percent": 61.9609,
      "rank_macro_f1_within_variant": 1,
      "phobert_only_macro_f1": 0.187029,
      "phobert_only_accuracy": 0.244157,
      "oracle_router_macro_f1": 0.300282,
      "oracle_router_accuracy": 0.432091,
      "macro_f1_gain_vs_phobert": 0.117103,
      "accuracy_gain_vs_phobert": 0.193619,
      "macro_f1_gap_to_oracle": -0.00385
    },
    {
      "task": "topic",
      "system": "oracle_router",
      "variant": "mixed_no_accent",
      "noise_type": "mixed",
      "noise_level": "medium",
      "num_samples": 3166,
      "accuracy": 0.432091,
      "macro_precision": 0.354265,
      "macro_recall": 0.359841,
      "macro_f1": 0.300282,
      "weighted_precision": 0.628551,
      "weighted_recall": 0.432091,
      "weighted_f1": 0.496427,
      "variant_order": 6,
      "clean_macro_f1": 0.800073,
      "variant_macro_f1": 0.300282,
      "macro_f1_drop": 0.499791,
      "macro_f1_relative_drop_percent": 62.4682,
      "rank_macro_f1_within_variant": 2,
      "phobert_only_macro_f1": 0.187029,
      "phobert_only_accuracy": 0.244157,
      "oracle_router_macro_f1": 0.300282,
      "oracle_router_accuracy": 0.432091,
      "macro_f1_gain_vs_phobert": 0.113253,
      "accuracy_gain_vs_phobert": 0.187934,
      "macro_f1_gap_to_oracle": 0.0
    },
    {
      "task": "topic",
      "system": "tfidf_char_svm_only",
      "variant": "mixed_no_accent",
      "noise_type": "mixed",
      "noise_level": "medium",
      "num_samples": 3166,
      "accuracy": 0.432091,
      "macro_precision": 0.354265,
      "macro_recall": 0.359841,
      "macro_f1": 0.300282,
      "weighted_precision": 0.628551,
      "weighted_recall": 0.432091,
      "weighted_f1": 0.496427,
      "variant_order": 6,
      "clean_macro_f1": 0.732207,
      "variant_macro_f1": 0.300282,
      "macro_f1_drop": 0.431925,
      "macro_f1_relative_drop_percent": 58.9895,
      "rank_macro_f1_within_variant": 2,
      "phobert_only_macro_f1": 0.187029,
      "phobert_only_accuracy": 0.244157,
      "oracle_router_macro_f1": 0.300282,
      "oracle_router_accuracy": 0.432091,
      "macro_f1_gain_vs_phobert": 0.113253,
      "accuracy_gain_vs_phobert": 0.187934,
      "macro_f1_gap_to_oracle": 0.0
    },
    {
      "task": "topic",
      "system": "phobert_only",
      "variant": "mixed_no_accent",
      "noise_type": "mixed",
      "noise_level": "medium",
      "num_samples": 3166,
      "accuracy": 0.244157,
      "macro_precision": 0.32741,
      "macro_recall": 0.310173,
      "macro_f1": 0.187029,
      "weighted_precision": 0.629254,
      "weighted_recall": 0.244157,
      "weighted_f1": 0.31136,
      "variant_order": 6,
      "clean_macro_f1": 0.800073,
      "variant_macro_f1": 0.187029,
      "macro_f1_drop": 0.613044,
      "macro_f1_relative_drop_percent": 76.6235,
      "rank_macro_f1_within_variant": 3,
      "phobert_only_macro_f1": 0.187029,
      "phobert_only_accuracy": 0.244157,
      "oracle_router_macro_f1": 0.300282,
      "oracle_router_accuracy": 0.432091,
      "macro_f1_gain_vs_phobert": 0.0,
      "accuracy_gain_vs_phobert": 0.0,
      "macro_f1_gap_to_oracle": 0.113253
    }
  ]
}